{
"gameglobals":
  [
    {"fps" : 60,
     "resolution" : [1280,720],
     "maprect" : [2000,1500],
     "backgroundimage":"gamedata/pictures/map.png",
     "gamemusic":"utils/Sounds/Ending Credits.wav"
    }
  ],
"player":
  [
    {"type" : "sprites.player",
     "image":"gamedata/pictures/Knight Sprite Sheet.png", 
     "position":[50,50],
     "ssinfo":[0,0,4,1,200,200,0,0]
    }
  ],
"blocks":
  [
    {"type" : "sprites.obstacle",
     "number" : 30,
     "image":"gamedata/pictures/house.png", 
     "randomrect" : [150,0,1850,1500],
     "size":[80,60]
    }
  ]
}

